<TPUs430><name>TPUs430</name><n_leds>37</n_leds><n_buttons>19</n_buttons><display><display_name>display</display_name><display_x>0</display_x><display_y>0</display_y><display_dimx>0</display_dimx><display_dimy>0</display_dimy></display><version>v16</version><leds><led1_name>Power</led1_name><led1_nColour>2</led1_nColour><led1_x>0</led1_x><led1_y>0</led1_y><led1_colours><led1_colour1>green</led1_colour1><led1_colour2>yellow</led1_colour2></led1_colours><led2_name>Run</led2_name><led2_nColour>2</led2_nColour><led2_x>0</led2_x><led2_y>0</led2_y><led2_colours><led2_colour1>green</led2_colour1><led2_colour2>red</led2_colour2></led2_colours><led3_name>Lan</led3_name><led3_nColour>2</led3_nColour><led3_x>0</led3_x><led3_y>0</led3_y><led3_colours><led3_colour1>green</led3_colour1><led3_colour2>yellow</led3_colour2></led3_colours><led4_name>L1</led4_name><led4_nColour>2</led4_nColour><led4_x>0</led4_x><led4_y>0</led4_y><led4_colours><led4_colour1>red</led4_colour1><led4_colour2>yellow</led4_colour2></led4_colours><led5_name>L2</led5_name><led5_nColour>2</led5_nColour><led5_x>0</led5_x><led5_y>0</led5_y><led5_colours><led5_colour1>red</led5_colour1><led5_colour2>yellow</led5_colour2></led5_colours><led6_name>L3</led6_name><led6_nColour>2</led6_nColour><led6_x>0</led6_x><led6_y>0</led6_y><led6_colours><led6_colour1>red</led6_colour1><led6_colour2>yellow</led6_colour2></led6_colours><led7_name>L4</led7_name><led7_nColour>2</led7_nColour><led7_x>0</led7_x><led7_y>0</led7_y><led7_colours><led7_colour1>red</led7_colour1><led7_colour2>yellow</led7_colour2></led7_colours><led8_name>L5</led8_name><led8_nColour>2</led8_nColour><led8_x>0</led8_x><led8_y>0</led8_y><led8_colours><led8_colour1>red</led8_colour1><led8_colour2>yellow</led8_colour2></led8_colours><led9_name>L6</led9_name><led9_nColour>2</led9_nColour><led9_x>0</led9_x><led9_y>0</led9_y><led9_colours><led9_colour1>red</led9_colour1><led9_colour2>yellow</led9_colour2></led9_colours><led10_name>L7</led10_name><led10_nColour>2</led10_nColour><led10_x>0</led10_x><led10_y>0</led10_y><led10_colours><led10_colour1>red</led10_colour1><led10_colour2>yellow</led10_colour2></led10_colours><led11_name>L8</led11_name><led11_nColour>2</led11_nColour><led11_x>0</led11_x><led11_y>0</led11_y><led11_colours><led11_colour1>red</led11_colour1><led11_colour2>yellow</led11_colour2></led11_colours><led12_name>L9</led12_name><led12_nColour>2</led12_nColour><led12_x>0</led12_x><led12_y>0</led12_y><led12_colours><led12_colour1>red</led12_colour1><led12_colour2>yellow</led12_colour2></led12_colours><led13_name>L10</led13_name><led13_nColour>2</led13_nColour><led13_x>0</led13_x><led13_y>0</led13_y><led13_colours><led13_colour1>red</led13_colour1><led13_colour2>yellow</led13_colour2></led13_colours><led14_name>L11</led14_name><led14_nColour>2</led14_nColour><led14_x>0</led14_x><led14_y>0</led14_y><led14_colours><led14_colour1>red</led14_colour1><led14_colour2>yellow</led14_colour2></led14_colours><led15_name>L12</led15_name><led15_nColour>2</led15_nColour><led15_x>0</led15_x><led15_y>0</led15_y><led15_colours><led15_colour1>red</led15_colour1><led15_colour2>yellow</led15_colour2></led15_colours><led16_name>L13</led16_name><led16_nColour>2</led16_nColour><led16_x>0</led16_x><led16_y>0</led16_y><led16_colours><led16_colour1>red</led16_colour1><led16_colour2>yellow</led16_colour2></led16_colours><led17_name>L14</led17_name><led17_nColour>2</led17_nColour><led17_x>0</led17_x><led17_y>0</led17_y><led17_colours><led17_colour1>red</led17_colour1><led17_colour2>yellow</led17_colour2></led17_colours><led18_name>L15</led18_name><led18_nColour>2</led18_nColour><led18_x>0</led18_x><led18_y>0</led18_y><led18_colours><led18_colour1>red</led18_colour1><led18_colour2>yellow</led18_colour2></led18_colours><led19_name>L16</led19_name><led19_nColour>2</led19_nColour><led19_x>0</led19_x><led19_y>0</led19_y><led19_colours><led19_colour1>red</led19_colour1><led19_colour2>yellow</led19_colour2></led19_colours><led20_name>F1L1</led20_name><led20_nColour>1</led20_nColour><led20_x>0</led20_x><led20_y>0</led20_y><led20_colours><led20_colour1>green</led20_colour1></led20_colours><led21_name>F1L2</led21_name><led21_nColour>1</led21_nColour><led21_x>0</led21_x><led21_y>0</led21_y><led21_colours><led21_colour1>red</led21_colour1></led21_colours><led22_name>F2L1</led22_name><led22_nColour>1</led22_nColour><led22_x>0</led22_x><led22_y>0</led22_y><led22_colours><led22_colour1>green</led22_colour1></led22_colours><led23_name>F2L2</led23_name><led23_nColour>1</led23_nColour><led23_x>0</led23_x><led23_y>0</led23_y><led23_colours><led23_colour1>red</led23_colour1></led23_colours><led24_name>F3L1</led24_name><led24_nColour>1</led24_nColour><led24_x>0</led24_x><led24_y>0</led24_y><led24_colours><led24_colour1>green</led24_colour1></led24_colours><led25_name>F3L2</led25_name><led25_nColour>1</led25_nColour><led25_x>0</led25_x><led25_y>0</led25_y><led25_colours><led25_colour1>red</led25_colour1></led25_colours><led26_name>F4L1</led26_name><led26_nColour>1</led26_nColour><led26_x>0</led26_x><led26_y>0</led26_y><led26_colours><led26_colour1>green</led26_colour1></led26_colours><led27_name>F4L2</led27_name><led27_nColour>1</led27_nColour><led27_x>0</led27_x><led27_y>0</led27_y><led27_colours><led27_colour1>red</led27_colour1></led27_colours><led28_name>F5L1</led28_name><led28_nColour>1</led28_nColour><led28_x>0</led28_x><led28_y>0</led28_y><led28_colours><led28_colour1>green</led28_colour1></led28_colours><led29_name>F5L2</led29_name><led29_nColour>1</led29_nColour><led29_x>0</led29_x><led29_y>0</led29_y><led29_colours><led29_colour1>red</led29_colour1></led29_colours><led30_name>F6L1</led30_name><led30_nColour>1</led30_nColour><led30_x>0</led30_x><led30_y>0</led30_y><led30_colours><led30_colour1>green</led30_colour1></led30_colours><led31_name>F6L2</led31_name><led31_nColour>1</led31_nColour><led31_x>0</led31_x><led31_y>0</led31_y><led31_colours><led31_colour1>red</led31_colour1></led31_colours><led32_name>F7L1</led32_name><led32_nColour>1</led32_nColour><led32_x>0</led32_x><led32_y>0</led32_y><led32_colours><led32_colour1>green</led32_colour1></led32_colours><led33_name>F7L2</led33_name><led33_nColour>1</led33_nColour><led33_x>0</led33_x><led33_y>0</led33_y><led33_colours><led33_colour1>red</led33_colour1></led33_colours><led34_name>F8L1</led34_name><led34_nColour>1</led34_nColour><led34_x>0</led34_x><led34_y>0</led34_y><led34_colours><led34_colour1>green</led34_colour1></led34_colours><led35_name>F8L2</led35_name><led35_nColour>1</led35_nColour><led35_x>0</led35_x><led35_y>0</led35_y><led35_colours><led35_colour1>red</led35_colour1></led35_colours><led36_name>F9L1</led36_name><led36_nColour>1</led36_nColour><led36_x>0</led36_x><led36_y>0</led36_y><led36_colours><led36_colour1>green</led36_colour1></led36_colours><led37_name>F9L2</led37_name><led37_nColour>1</led37_nColour><led37_x>0</led37_x><led37_y>0</led37_y><led37_colours><led37_colour1>red</led37_colour1></led37_colours></leds><buttons><button1_name>ON</button1_name><button1_x>0</button1_x><button1_y>0</button1_y><button2_name>OFF</button2_name><button2_x>0</button2_x><button2_y>0</button2_y><button3_name>SEL</button3_name><button3_x>0</button3_x><button3_y>0</button3_y><button4_name>CLR</button4_name><button4_x>0</button4_x><button4_y>0</button4_y><button5_name>C</button5_name><button5_x>0</button5_x><button5_y>0</button5_y><button6_name>E</button6_name><button6_x>0</button6_x><button6_y>0</button6_y><button7_name>F1</button7_name><button7_x>0</button7_x><button7_y>0</button7_y><button8_name>F2</button8_name><button8_x>0</button8_x><button8_y>0</button8_y><button9_name>F3</button9_name><button9_x>0</button9_x><button9_y>0</button9_y><button10_name>F4</button10_name><button10_x>0</button10_x><button10_y>0</button10_y><button11_name>F5</button11_name><button11_x>0</button11_x><button11_y>0</button11_y><button12_name>F6</button12_name><button12_x>0</button12_x><button12_y>0</button12_y><button13_name>F7</button13_name><button13_x>0</button13_x><button13_y>0</button13_y><button14_name>F8</button14_name><button14_x>0</button14_x><button14_y>0</button14_y><button15_name>F9</button15_name><button15_x>0</button15_x><button15_y>0</button15_y><button16_name>UP</button16_name><button16_x>0</button16_x><button16_y>0</button16_y><button17_name>LEFT</button17_name><button17_x>0</button17_x><button17_y>0</button17_y><button18_name>RIGHT</button18_name><button18_x>0</button18_x><button18_y>0</button18_y><button19_name>DOWN</button19_name><button19_x>0</button19_x><button19_y>0</button19_y></buttons></TPUs430>